specular/__init__.py
specular_ai-0.2.1.dist-info/METADATA
specular_ai-0.2.1.dist-info/WHEEL
specular_ai-0.2.1.dist-info/RECORD
