Metadata-Version: 2.4
Name: specular-ai
Version: 0.2.1
Summary: MOVED: This package has been renamed to 'specsoloist'.
Author-email: Toby Lightheart <code@symbolfarm.com>
License-Expression: MIT
Classifier: Development Status :: 7 - Inactive
Classifier: Intended Audience :: Developers
Classifier: License :: OSI Approved :: MIT License
Classifier: Topic :: Software Development :: Code Generators
Requires-Python: >=3.10
Requires-Dist: specsoloist>=0.2.0
